aquila_borg/utils.py
aquila_borg/_borg.cpython-310-x86_64-linux-gnu.so
aquila_borg/__init__.py
aquila_borg/dft.py
aquila_borg/borg_native.py
aquila_borg-2.1.2.dist-info/RECORD
aquila_borg-2.1.2.dist-info/License_CeCILL_V2.1.txt
aquila_borg-2.1.2.dist-info/METADATA
aquila_borg-2.1.2.dist-info/WHEEL
aquila_borg-2.1.2.dist-info/License_GPL-3.0.txt
aquila_borg-2.1.2.dist-info/top_level.txt
aquila_borg.libs/libgomp-a34b3233.so.1.0.0
