Metadata-Version: 2.1
Name: aquila_borg
Version: 2.1.2
Summary: ARES/BORG engine packaged in a Python module
Keywords: cosmology,inference,simulation,statistics
Classifier: Intended Audience :: Developers
Classifier: Natural Language :: English
Classifier: License :: OSI Approved :: GNU Lesser General Public License v3 (LGPLv3)
Classifier: License :: OSI Approved :: CEA CNRS Inria Logiciel Libre License, version 2.1 (CeCILL-2.1)
Classifier: Programming Language :: C
Classifier: Programming Language :: C++
Classifier: Programming Language :: Python
Classifier: Programming Language :: Python :: 3
Classifier: Programming Language :: Python :: Implementation :: CPython
Requires-Python: >=3.6
License-File: License_CeCILL_V2.1.txt
License-File: License_GPL-3.0.txt
Requires-Dist: numpy
Requires-Dist: deprecated
